slack_mcp/__init__.py
slack_mcp/events.py
slack_mcp/py.typed
slack_mcp/types.README.md
slack_mcp/types.py
slack_mcp/_base/__init__.py
slack_mcp/_base/app.py
slack_mcp/client/__init__.py
slack_mcp/client/factory.py
slack_mcp/client/manager.py
slack_mcp/integrate/__init__.py
slack_mcp/integrate/app.py
slack_mcp/integrate/server.py
slack_mcp/logging/__init__.py
slack_mcp/logging/config.py
slack_mcp/mcp/__init__.py
slack_mcp/mcp/__main__.py
slack_mcp/mcp/app.py
slack_mcp/mcp/entry.py
slack_mcp/mcp/server.py
slack_mcp/mcp/cli/__init__.py
slack_mcp/mcp/cli/models.py
slack_mcp/mcp/cli/options.py
slack_mcp/mcp/model/__init__.py
slack_mcp/mcp/model/input.py
slack_mcp/webhook/__init__.py
slack_mcp/webhook/__main__.py
slack_mcp/webhook/app.py
slack_mcp/webhook/entry.py
slack_mcp/webhook/models.py
slack_mcp/webhook/server.py
slack_mcp/webhook/cli/__init__.py
slack_mcp/webhook/cli/models.py
slack_mcp/webhook/cli/options.py
slack_mcp/webhook/event/__init__.py
slack_mcp/webhook/event/consumer.py
slack_mcp/webhook/event/handler/__init__.py
slack_mcp/webhook/event/handler/base.py
slack_mcp/webhook/event/handler/decorator.py
slack_mcp-0.1.0.dist-info/METADATA
slack_mcp-0.1.0.dist-info/WHEEL
slack_mcp-0.1.0.dist-info/entry_points.txt
slack_mcp-0.1.0.dist-info/licenses/LICENSE
slack_mcp-0.1.0.dist-info/RECORD
