Metadata-Version: 2.4
Name: slack-mcp
Version: 0.1.0
Summary: 🦾 A strong MCP server for Slack.
Project-URL: Homepage, https://github.com/Chisanan232/slack-mcp-server
Project-URL: Repository, https://github.com/Chisanan232/slack-mcp-server
Project-URL: Documentation, https://chisanan232.github.io/slack-mcp-server/
Project-URL: Changelog, https://chisanan232.github.io/slack-mcp-server/docs/next/changelog
Project-URL: Project Management, https://app.clickup.com/9018752317/v/f/90185744047/90184991515
Author-email: Chisanan232 <chi10211201@cycu.org.tw>
License: 
License-File: LICENSE
Keywords: mcp,mcp-server,slack,slack-mcp,slack-mcp-server
Classifier: Development Status :: 3 - Alpha
Classifier: Intended Audience :: Developers
Classifier: License :: OSI Approved :: MIT License
Classifier: Operating System :: OS Independent
Classifier: Programming Language :: Python :: 3
Classifier: Programming Language :: Python :: 3.12
Classifier: Programming Language :: Python :: 3.13
Classifier: Topic :: Software Development :: Libraries :: Python Modules
Classifier: Topic :: Utilities
Requires-Python: <3.14,>=3.12
Requires-Dist: abstract-backend>=0.0.1
Provides-Extra: all
Requires-Dist: fastapi>=0.116.1; extra == 'all'
Requires-Dist: mcp[cli]>=1.10.1; extra == 'all'
Requires-Dist: pydantic>=2.11.7; extra == 'all'
Requires-Dist: slack-sdk>=3.36.0; extra == 'all'
Requires-Dist: uvicorn>=0.35.0; extra == 'all'
Provides-Extra: mcp
Requires-Dist: mcp[cli]>=1.10.1; extra == 'mcp'
Requires-Dist: pydantic>=2.11.7; extra == 'mcp'
Requires-Dist: slack-sdk>=3.36.0; extra == 'mcp'
Provides-Extra: webhook
Requires-Dist: fastapi>=0.116.1; extra == 'webhook'
Requires-Dist: pydantic>=2.11.7; extra == 'webhook'
Requires-Dist: uvicorn>=0.35.0; extra == 'webhook'
